pprofile_ext/__init__.py
pprofile_ext/driver.py
pprofile_ext/handlers.py
pprofile_ext/parsers.py
pprofile_ext/util.py
pprofile_ext/html/__init__.py
pprofile_ext/html/file.py
pprofile_ext/html/summary.py
pprofile_ext-1.0.5.dist-info/LICENSE.txt
pprofile_ext-1.0.5.dist-info/METADATA
pprofile_ext-1.0.5.dist-info/WHEEL
pprofile_ext-1.0.5.dist-info/top_level.txt
pprofile_ext-1.0.5.dist-info/RECORD
